[
  {
    "id": 1,
    "name": "laptop",
    "variants": [
      {
        "SKU": "LAP-TECH-VA1-12",
        "name": "var 1",
        "quantity": 21,
        "value": 10,
        "qr": true
      },
      {
        "SKU": "LAP-TECH-VA2-12",
        "name": "var 2",
        "quantity": 31213,
        "value": 252520,
        "qr": false
      }
    ]
  },
  {
    "id": 2,
    "name": "book",
    "variants": [
      {
        "SKU": "BOO-LIB-VA0-44",
        "name": "var 0",
        "quantity": 3,
        "value": 9000,
        "qr": true
      }
    ]
  },
  {
    "id": 3,
    "name": "lamp",
    "variants": [
      {
        "SKU": "LAM-HOM-RED-00",
        "name": "red",
        "quantity": 3,
        "value": 100,
        "qr": false
      }
    ]
  }
]